jupyterlab_lsstextensions/__init__.py
jupyterlab_lsstextensions/handlers.py
jupyterlab_lsstextensions/templatemap.py
jupyterlab_lsstextensions-2.0.0.dist-info/LICENSE
jupyterlab_lsstextensions-2.0.0.dist-info/METADATA
jupyterlab_lsstextensions-2.0.0.dist-info/WHEEL
jupyterlab_lsstextensions-2.0.0.dist-info/top_level.txt
jupyterlab_lsstextensions-2.0.0.dist-info/RECORD
