Metadata-Version: 2.1
Name: jupyterlab-lsstextensions
Version: 2.0.0
Summary: UNKNOWN
Home-page: UNKNOWN
Author: UNKNOWN
Author-email: UNKNOWN
License: UNKNOWN
Platform: UNKNOWN
Requires-Dist: nbreport (>=0.7.3)
Requires-Dist: notebook
